<?xml version="1.0" encoding="utf-8"?>

<VenuePool>
<Venue>
<venueId>1</venueId>
<location>MPSH1</location>
<capacity>50</capacity>
</Venue>
<Venue>
<venueId>2</venueId>
<location>MPSH2</location>
<capacity>50</capacity>
</Venue>
<Venue>
<venueId>3</venueId>
<location>MPSH3</location>
<capacity>50</capacity>
</Venue>
<Venue>
<venueId>4</venueId>
<location>MPSH4</location>
<capacity>150</capacity>
</Venue>
<Venue>
<venueId>5</venueId>
<location>MPSH5</location>
<capacity>250</capacity>
</Venue>
<Venue>
<venueId>6</venueId>
<location>MPSH6</location>
<capacity>450</capacity>
</Venue>
</VenuePool>